SimpleUpdater/SimpleUpdater.py
SimpleUpdater/__init__.py
SimpleUpdater/check.py
SimpleUpdater/download.py
simpleupdater-0.1.3.dist-info/LICENSE
simpleupdater-0.1.3.dist-info/METADATA
simpleupdater-0.1.3.dist-info/WHEEL
simpleupdater-0.1.3.dist-info/top_level.txt
simpleupdater-0.1.3.dist-info/RECORD
