Metadata-Version: 2.1
Name: simpleupdater
Version: 0.1.3
Summary: Seamlessly update your software with ease using this lightweight Python module
Home-page: https://github.com/mvishok/SimpleUpdater
Author: Vishok M
Author-email: 
Project-URL: Bug Tracker, https://github.com/mvishok/SimpleUpdater/issues
Classifier: Programming Language :: Python :: 3
Classifier: License :: OSI Approved :: MIT License
Classifier: Operating System :: OS Independent
Requires-Python: >=3.6
License-File: LICENSE
